lab6demo/__init__.py
lab6demo/lab6demo.py
lab6demo/utils.py
lab6demo-0.0.3.dist-info/LICENSE
lab6demo-0.0.3.dist-info/METADATA
lab6demo-0.0.3.dist-info/WHEEL
lab6demo-0.0.3.dist-info/dependency_links.txt
lab6demo-0.0.3.dist-info/top_level.txt
lab6demo-0.0.3.dist-info/RECORD
