Metadata-Version: 2.1
Name: lab6demo
Version: 0.0.3
Summary: A python package for interactive mapping
Home-page: https://github.com/crose26/lab6demo
Author: Caleb Rose
Author-email: crose26@vols.utk.edu
License: MIT license
Keywords: lab6demo
Platform: UNKNOWN
Classifier: Development Status :: 2 - Pre-Alpha
Classifier: Intended Audience :: Developers
Classifier: License :: OSI Approved :: MIT License
Classifier: Natural Language :: English
Classifier: Programming Language :: Python :: 3
Classifier: Programming Language :: Python :: 3.5
Classifier: Programming Language :: Python :: 3.6
Classifier: Programming Language :: Python :: 3.7
Classifier: Programming Language :: Python :: 3.8
Requires-Python: >=3.5
Requires-Dist: folium
Requires-Dist: ipyleaflet
Requires-Dist: pyshp
